LICENSE
README.md
pyproject.toml
setup.py
xrequests/__init__.py
xrequests.egg-info/PKG-INFO
xrequests.egg-info/SOURCES.txt
xrequests.egg-info/dependency_links.txt
xrequests.egg-info/requires.txt
xrequests.egg-info/top_level.txt